poster_template/__init__.py
poster_template/coordiante.py
poster_template/image_utils.py
poster_template/mask.py
poster_template/template.py
poster_template-0.2.3.dist-info/METADATA
poster_template-0.2.3.dist-info/WHEEL
poster_template-0.2.3.dist-info/top_level.txt
poster_template-0.2.3.dist-info/RECORD
