Metadata-Version: 2.1
Name: poster_template
Version: 0.2.3
Summary: A simple example package
Home-page: https://github.com/geekforai/poster_template
Author: Amit Kumar
Author-email: amit.ceg.official@gmail.com
Classifier: Programming Language :: Python :: 3
Classifier: License :: OSI Approved :: MIT License
Classifier: Operating System :: OS Independent
Requires-Dist: pillow
Requires-Dist: numpy
